teleinfo_exporter/__init__.py
teleinfo_exporter/__main__.py
teleinfo_exporter/app.py
teleinfo_exporter-1.2.0.dist-info/LICENSE
teleinfo_exporter-1.2.0.dist-info/METADATA
teleinfo_exporter-1.2.0.dist-info/WHEEL
teleinfo_exporter-1.2.0.dist-info/entry_points.txt
teleinfo_exporter-1.2.0.dist-info/top_level.txt
teleinfo_exporter-1.2.0.dist-info/RECORD
