Metadata-Version: 2.1
Name: teleinfo-exporter
Version: 1.2.0
Summary: Simple prometheus exporter for Linky teleinfo.
Author-email: d3vyce <contact@d3vyce.fr>
License: MIT License
Project-URL: Homepage, https://github.com/d3vyce/teleinfo-exporter
Project-URL: Repository, https://github.com/d3vyce/teleinfo-exporter.git
Project-URL: Issues, https://github.com/d3vyce/teleinfo-exporter/issues
Project-URL: Changelog, https://github.com/d3vyce/teleinfo-exporter/blob/main/CHANGELOG.md
Keywords: teleinfo,linky,prometheus,exporter
Classifier: Programming Language :: Python :: 3
Classifier: License :: OSI Approved :: MIT License
Classifier: Operating System :: OS Independent
Requires-Python: >=3.8
License-File: LICENSE
Requires-Dist: bcrypt ~=4.1
Requires-Dist: configargparse ~=1.7
Requires-Dist: flask ~=3.0
Requires-Dist: flask-httpauth ~=4.8
Requires-Dist: paho-mqtt ~=1.6
Requires-Dist: prometheus-client ~=0.19
